gener8/__init__.py
gener8/data_connector.py
gener8/engine.py
gener8/evaluation.py
gener8/generator.py
gener8/trainer.py
gener8_synth-0.1.0.dist-info/licenses/LICENSE
gener8_synth-0.1.0.dist-info/METADATA
gener8_synth-0.1.0.dist-info/WHEEL
gener8_synth-0.1.0.dist-info/top_level.txt
gener8_synth-0.1.0.dist-info/RECORD
