Metadata-Version: 2.4
Name: gener8-synth
Version: 0.1.0
Summary: A synthetic data generation engine
Home-page: https://github.com/Abdulrahman0044/gener8
Author: Abdulrahman Abdulrahman
Author-email: abdulrahamanbabatunde12@gmail.com
License: Apache-2.0
Classifier: Programming Language :: Python :: 3
Classifier: Programming Language :: Python :: 3.8
Classifier: Programming Language :: Python :: 3.9
Classifier: Programming Language :: Python :: 3.10
Classifier: Programming Language :: Python :: 3.11
Classifier: Programming Language :: Python :: 3.12
Classifier: License :: OSI Approved :: Apache Software License
Classifier: Operating System :: OS Independent
Requires-Python: >=3.8
License-File: LICENSE
Requires-Dist: pandas>=1.5.0
Requires-Dist: numpy<2.0,>=1.23.0
Requires-Dist: scikit-learn>=1.1.0
Requires-Dist: torch>=1.13.0
Requires-Dist: matplotlib>=3.5.0
Requires-Dist: seaborn>=0.11.0
Dynamic: author
Dynamic: author-email
Dynamic: classifier
Dynamic: description
Dynamic: description-content-type
Dynamic: home-page
Dynamic: license
Dynamic: license-file
Dynamic: requires-dist
Dynamic: requires-python
Dynamic: summary
